mahdi/__init__.py
Mahdi-0.1.dist-info/LICENSE
Mahdi-0.1.dist-info/METADATA
Mahdi-0.1.dist-info/WHEEL
Mahdi-0.1.dist-info/top_level.txt
Mahdi-0.1.dist-info/RECORD
