Metadata-Version: 2.1
Name: Mahdi
Version: 0.1
Summary: this is a simple pip modul and test
License-File: LICENSE
